{
    "nei na": {
        "description": "",
        "tags": [
            ""
        ],
        "translations": [
            "chat"
        ],
        "type": "simple noun"
    },
    "nei": {
        "description": "I wanna jump and run everywhere",
        "tags": [],
        "translations": [
            "agile",
            "energetic"
        ],
        "type": "color"
    },
    "na": {
        "description": "someone (human, animal) you can have meamingful interactions with",
        "tags": [],
        "translations": [
            "il",
            "elle"
        ],
        "type": "class"
    },
    "sei": {
        "description": "",
        "tags": [
            ""
        ],
        "translations": [
            "bavard",
            "parlant"
        ],
        "type": "color"
    },
    "sei so": {
        "description": "quelque chose qui a ete dit. C'est aussi le nom de la langue.",
        "tags": [],
        "translations": [
            "parler",
            "mots",
            "phrase"
        ],
        "type": "simple noun"
    },
    "leeso": {
        "description": "",
        "tags": [],
        "translations": [
            "peser sur"
        ],
        "type": "color"
    },
    "leeso na": {
        "description": "",
        "tags": [
            ""
        ],
        "translations": [
            "vache",
            "boeuf"
        ],
        "type": "simple noun"
    },
    "leeso til": {
        "description": "",
        "tags": [
            ""
        ],
        "translations": [
            "boeuf",
            "vache"
        ],
        "type": "simple noun"
    },
    "til": {
        "description": "",
        "tags": [],
        "translations": [
            "animal"
        ],
        "type": "class"
    },
    "sja": {
        "description": "",
        "tags": [],
        "translations": [
            "sucre",
            "doux"
        ],
        "type": "color"
    },
    "ga": {
        "description": "nourriture \"lourde\", riche en graisse, proteines, surcres, ou au gout caracteristique peu acide : farines, viandes, patisseries, beurre, ...",
        "tags": [],
        "translations": [
            "nourriture"
        ],
        "type": "class"
    },
    "leeso ga": {
        "description": "",
        "tags": [
            ""
        ],
        "translations": [
            "boeuf"
        ],
        "type": "simple noun"
    },
    "lp": {
        "description": "",
        "tags": [],
        "translations": [
            "surface plane"
        ],
        "type": "class"
    },
    "tc": {
        "description": "",
        "tags": [],
        "translations": [],
        "type": "class"
    },
    "jus": {
        "description": "",
        "tags": [],
        "translations": [],
        "type": "class"
    },
    "so": {
        "description": "Contenu qui a du sens",
        "tags": [
            ""
        ],
        "translations": [
            "mots",
            "parole",
            "texte"
        ],
        "type": "class"
    },
    "nalc": {
        "description": "",
        "tags": [],
        "translations": [
            "reussir a attraper"
        ],
        "type": "color"
    },
    "nalc jus": {
        "description": "",
        "tags": [
            ""
        ],
        "translations": [
            "main"
        ],
        "type": "simple noun"
    },
    "eli lp": {
        "description": "tout ce qui ressemble a une surface d'eau",
        "tags": [],
        "translations": [
            "mer",
            "lac",
            "eau",
            "ocean",
            "etang"
        ],
        "type": "simple noun"
    },
    "eli": {
        "description": "se sentir trempe, etre trempe",
        "tags": [],
        "translations": [
            "mouiller",
            "humide"
        ],
        "type": "color"
    },
    "qispe": {
        "description": "intention de communiquer en faisant un effort d'engravement sur un support",
        "tags": [],
        "translations": [],
        "type": "color"
    },
    "qispe so": {
        "description": "",
        "tags": [],
        "translations": [
            "texte",
            "ecrire",
            "ecriture"
        ],
        "type": "simple noun"
    },
    "lam": {
        "description": "",
        "tags": [],
        "translations": [],
        "type": "class"
    },
    "sai": {
        "description": "",
        "tags": [],
        "translations": [],
        "type": "class"
    },
    "ki": {
        "description": "",
        "tags": [],
        "translations": [
            "apparence"
        ],
        "type": "class"
    },
    "ko": {
        "description": "",
        "tags": [],
        "translations": [
            "conteneur"
        ],
        "type": "class"
    },
    "sak": {
        "description": "",
        "tags": [
            ""
        ],
        "translations": [
            "poudre"
        ],
        "type": "class"
    },
    "kju": {
        "description": "",
        "tags": [],
        "translations": [
            "comportement"
        ],
        "type": "class"
    },
    "fjp": {
        "description": "valeur abstraite, donnee d'evaluation, de placement sur echelle, sur relation",
        "tags": [],
        "translations": [
            "valeur"
        ],
        "type": "class"
    },
    "min": {
        "description": "",
        "tags": [],
        "translations": [],
        "type": "class"
    },
    "fsu": {
        "description": "avoir l'impression de perdre son temps en participant a une activite",
        "tags": [],
        "translations": [],
        "type": "color"
    },
    "sbn": {
        "description": "",
        "tags": [],
        "translations": [],
        "type": "class"
    },
    "si": {
        "description": "structure construite qui realise automatiquement une action sans avoir besoin d'une interaction humaine (idee d'automatisme)",
        "tags": [],
        "translations": [
            "machine",
            "appareil"
        ],
        "type": "class"
    },
    "slui": {
        "description": "liquide buvable, source de liquide potable",
        "tags": [
            ""
        ],
        "translations": [
            "potable",
            "liquide"
        ],
        "type": "class"
    },
    "eli slui": {
        "description": "eau \u00e0 boire, verre d'eau",
        "tags": [
            ""
        ],
        "translations": [
            "eau",
            "boisson",
            "verre"
        ],
        "type": "simple noun"
    },
    "sja sak": {
        "description": "",
        "tags": [
            ""
        ],
        "translations": [
            "sucre"
        ],
        "type": "simple noun"
    },
    "sja slui": {
        "description": "jus de fruits, boissons sucrees...",
        "type": "simple noun",
        "tags": [],
        "translations": [
            "jus de fruits",
            "boisson"
        ]
    },
    "nas": {
        "description": "",
        "tags": [
            "couleur"
        ],
        "translations": [
            "orange"
        ],
        "type": "color"
    },
    "tal": {
        "description": "",
        "tags": [
            "couleur"
        ],
        "translations": [
            "rouge"
        ],
        "type": "color"
    },
    "tal ki": {
        "description": "",
        "tags": [
            ""
        ],
        "translations": [
            "rouge"
        ],
        "type": "simple noun"
    },
    "nas ki": {
        "description": "",
        "tags": [
            ""
        ],
        "translations": [
            "orange"
        ],
        "type": "simple noun"
    },
    "nas ga": {
        "description": "",
        "tags": [
            ""
        ],
        "translations": [
            "mais"
        ],
        "type": "simple noun"
    },
    "nei na sai": {
        "description": "",
        "tags": [
            ""
        ],
        "translations": [
            "miaulement"
        ],
        "type": "simple noun"
    },
    "tsis": {
        "description": "sentir les grains de sable sur sa peau",
        "tags": [],
        "translations": [
            "granuleux",
            "poudreux",
            "sable"
        ],
        "type": "color"
    },
    "tsis sak": {
        "description": "",
        "tags": [
            ""
        ],
        "translations": [
            "sable",
            "poussiere"
        ],
        "type": "simple noun"
    },
    "tsis lp": {
        "description": "",
        "tags": [],
        "translations": [
            "plage",
            "sable"
        ],
        "type": "simple noun"
    },
    "fsu lam": {
        "description": "",
        "tags": [],
        "translations": [
            "ennui"
        ],
        "type": "simple noun"
    },
    "sja lam": {
        "description": "bonheur agreable, presque tranquille",
        "tags": [],
        "translations": [
            "soothing"
        ],
        "type": "simple noun"
    },
    "sei lam": {
        "description": "",
        "tags": [],
        "translations": [],
        "type": "simple noun"
    },
    "nei sbn": {
        "description": "",
        "tags": [
            ""
        ],
        "translations": [
            "effleurer"
        ],
        "type": "simple noun"
    },
    "nei lam": {
        "description": "",
        "tags": [],
        "translations": [
            "actif",
            "energetique"
        ],
        "type": "simple noun"
    },
    "qwbn": {
        "description": "se sentir flotter, nager lentement ou rester inerte, regarder un paysage comme le ciel ou le fond de l'eau",
        "tags": [],
        "translations": [
            "tranquille"
        ],
        "type": "color"
    },
    "qwbn ga": {
        "description": "",
        "tags": [],
        "translations": [
            "poisson"
        ],
        "type": "simple noun"
    },
    "nukse": {
        "description": "",
        "tags": [],
        "translations": [],
        "type": "color"
    },
    "nukse na": {
        "description": "",
        "tags": [],
        "translations": [],
        "type": "simple noun"
    },
    "nukse lam": {
        "description": "",
        "tags": [],
        "translations": [
            "detente",
            "detendu"
        ],
        "type": "simple noun"
    },
    "nukse min": {
        "description": "",
        "tags": [],
        "translations": [
            "moment calme"
        ],
        "type": "simple noun"
    },
    "jo lam": {
        "description": "",
        "tags": [],
        "translations": [
            "se sentir en avance"
        ],
        "type": "simple noun"
    },
    "jo": {
        "description": "",
        "tags": [],
        "translations": [
            "1st",
            "first",
            "one"
        ],
        "type": "numeral"
    },
    "ta": {
        "description": "",
        "tags": [],
        "translations": [
            "2nd",
            "second",
            "two"
        ],
        "type": "numeral"
    },
    "kje": {
        "description": "",
        "tags": [],
        "translations": [
            "3rd",
            "third",
            "three",
            "3"
        ],
        "type": "numeral"
    },
    "djyn": {
        "description": "",
        "tags": [],
        "translations": [
            "4th",
            "fourth",
            "4",
            "four"
        ],
        "type": "numeral"
    },
    "dy": {
        "description": "",
        "tags": [],
        "translations": [
            "5th",
            "5"
        ],
        "type": "numeral"
    },
    "(si)": {
        "description": "prefixe numerateur pour nombres disjonctifs",
        "tags": [],
        "translations": [],
        "type": "numeral"
    },
    "y": {
        "description": "",
        "tags": [],
        "translations": [
            "last",
            "1"
        ],
        "type": "numeral"
    },
    "din": {
        "description": "",
        "tags": [],
        "translations": [
            "2"
        ],
        "type": "numeral"
    },
    "khe_": {
        "description": "",
        "tags": [],
        "translations": [
            "3"
        ],
        "type": "numeral"
    },
    "sa_": {
        "description": "",
        "tags": [],
        "translations": [
            "4"
        ],
        "type": "numeral"
    },
    "(sb)": {
        "description": "",
        "tags": [],
        "translations": [
            "5th last",
            "5"
        ],
        "type": "numeral"
    },
    "(ja)": {
        "description": "prefixe numerateur pour nombres inverses",
        "tags": [],
        "translations": [],
        "type": "numeral"
    },
    "(to)": {
        "description": "",
        "tags": [],
        "translations": [
            "0",
            "zero"
        ],
        "type": "numeral"
    },
    "tb": {
        "description": "",
        "tags": [],
        "translations": [
            "1",
            "one"
        ],
        "type": "numeral"
    },
    "sa": {
        "description": "",
        "tags": [],
        "translations": [
            "2",
            "two"
        ],
        "type": "numeral"
    },
    "kb": {
        "description": "",
        "tags": [],
        "translations": [
            "3",
            "trois",
            "three"
        ],
        "type": "numeral"
    },
    "qu": {
        "description": "",
        "tags": [],
        "translations": [
            "4",
            "fourth",
            "quatre"
        ],
        "type": "numeral"
    },
    "(qa)": {
        "description": "",
        "tags": [],
        "translations": [
            "5"
        ],
        "type": "numeral"
    },
    "qe": {
        "description": "",
        "tags": [],
        "translations": [
            "6"
        ],
        "type": "numeral"
    },
    "ti": {
        "description": "",
        "tags": [],
        "translations": [
            "7"
        ],
        "type": "numeral"
    },
    "tsi": {
        "description": "",
        "tags": [],
        "translations": [
            "8"
        ],
        "type": "numeral"
    },
    "fe": {
        "description": "",
        "tags": [],
        "translations": [
            "9"
        ],
        "type": "numeral"
    },
    "te": {
        "description": "",
        "tags": [],
        "translations": [
            "10"
        ],
        "type": "numeral"
    },
    "(ko)": {
        "description": "",
        "tags": [],
        "translations": [
            "none",
            "zero",
            "0"
        ],
        "type": "numeral"
    },
    "nb": {
        "description": "",
        "tags": [],
        "translations": [
            "unique",
            "solo",
            "1"
        ],
        "type": "numeral"
    },
    "tsa": {
        "description": "",
        "tags": [],
        "translations": [
            "paire",
            "2"
        ],
        "type": "numeral"
    },
    "khe": {
        "description": "",
        "tags": [],
        "translations": [
            "3",
            "triple",
            "triplet"
        ],
        "type": "numeral"
    },
    "de": {
        "description": "",
        "tags": [],
        "translations": [
            "4",
            "quadruple"
        ],
        "type": "numeral"
    },
    "ul": {
        "description": "",
        "tags": [],
        "translations": [
            "5"
        ],
        "type": "numeral"
    },
    "den": {
        "description": "",
        "tags": [],
        "translations": [
            "6"
        ],
        "type": "numeral"
    },
    "het": {
        "description": "",
        "tags": [],
        "translations": [
            "7"
        ],
        "type": "numeral"
    },
    "kvw": {
        "description": "",
        "tags": [],
        "translations": [
            "8"
        ],
        "type": "numeral"
    },
    "feh": {
        "description": "",
        "tags": [],
        "translations": [
            "9"
        ],
        "type": "numeral"
    },
    "ka": {
        "description": "",
        "tags": [
            "statif",
            "positif"
        ],
        "translations": [],
        "type": "state"
    },
    "to": {
        "description": "",
        "tags": [
            "statif",
            "negatif"
        ],
        "translations": [],
        "type": "state"
    },
    "kto": {
        "description": "",
        "tags": [
            "statif",
            "question"
        ],
        "translations": [],
        "type": "state"
    },
    "ksa": {
        "description": "",
        "tags": [
            "transitionnel",
            "positif"
        ],
        "translations": [],
        "type": "state"
    },
    "tso": {
        "description": "",
        "tags": [
            "transitionnel",
            "negatif"
        ],
        "translations": [],
        "type": "state"
    },
    "qi": {
        "description": "",
        "tags": [
            "question"
        ],
        "translations": [],
        "type": "special"
    },
    "-qaj": {
        "description": "",
        "tags": [
            "suffixe"
        ],
        "translations": [],
        "type": "special"
    },
    "-qe": {
        "description": "",
        "tags": [
            "suffixe"
        ],
        "translations": [],
        "type": "special"
    },
    "-u": {
        "description": "",
        "tags": [
            "suffixe"
        ],
        "translations": [],
        "type": "special"
    },
    "-uo": {
        "description": "",
        "tags": [
            "suffixe"
        ],
        "translations": [],
        "type": "special"
    },
    "e": {
        "description": "",
        "tags": [],
        "translations": [
            "je"
        ],
        "type": "pronoun"
    },
    "tai": {
        "description": "",
        "tags": [],
        "translations": [
            "tu"
        ],
        "type": "pronoun"
    },
    "(ta)": {
        "description": "",
        "tags": [],
        "translations": [
            "vous"
        ],
        "type": "pronoun"
    },
    "(la)": {
        "description": "",
        "tags": [],
        "translations": [
            "il",
            "elle"
        ],
        "type": "pronoun"
    },
    "lai": {
        "description": "",
        "tags": [],
        "translations": [
            "il"
        ],
        "type": "pronoun"
    },
    "(lo)": {
        "description": "",
        "tags": [],
        "translations": [
            "autres"
        ],
        "type": "pronoun"
    },
    "lo": {
        "description": "",
        "tags": [
            "selecteur"
        ],
        "translations": [
            "autres"
        ],
        "type": "special"
    },
    "la": {
        "description": "",
        "tags": [
            "selecteur"
        ],
        "translations": [
            "demonstratif"
        ],
        "type": "special"
    },
    "fju": {
        "description": "",
        "tags": [
            "quantite"
        ],
        "translations": [
            "quantite ordinaire"
        ],
        "type": "special"
    },
    "nju": {
        "description": "",
        "tags": [
            "quantite"
        ],
        "translations": [
            "beaucoup"
        ],
        "type": "special"
    },
    "a": {
        "description": "",
        "tags": [
            "quantite"
        ],
        "translations": [
            "peu"
        ],
        "type": "special"
    },
    "nu": {
        "description": "",
        "tags": [
            "quantite"
        ],
        "translations": [
            "all"
        ],
        "type": "special"
    },
    "bien-famille": {
        "description": "",
        "tags": [
            "p"
        ],
        "translations": [],
        "type": "color"
    },
    "bien-village": {
        "description": "",
        "tags": [
            "p"
        ],
        "translations": [],
        "type": "color"
    },
    "bien-entreprise": {
        "description": "",
        "tags": [
            "p"
        ],
        "translations": [],
        "type": "color"
    },
    "bien-pays": {
        "description": "",
        "tags": [
            "p"
        ],
        "translations": [],
        "type": "color"
    },
    "sflu": {
        "description": "",
        "tags": [],
        "translations": [
            "plouf"
        ],
        "type": "color"
    },
    "sflu na": {
        "description": "",
        "tags": [],
        "translations": [
            "poisson"
        ],
        "type": "simple noun"
    },
    "sflu sai": {
        "description": "",
        "tags": [],
        "translations": [
            "plouf"
        ],
        "type": "simple noun"
    },
    "yfan": {
        "description": "",
        "tags": [],
        "translations": [
            "spongieux"
        ],
        "type": "color"
    },
    "yfan ga": {
        "description": "",
        "tags": [],
        "translations": [
            "gateau"
        ],
        "type": "simple noun"
    },
    "tas tc": {
        "description": "",
        "tags": [],
        "translations": [
            "bateau"
        ],
        "type": "simple noun"
    },
    "tas": {
        "description": "sensation du large, le vent marin",
        "tags": [],
        "translations": [],
        "type": "color"
    },
    "tas na": {
        "description": "oiseaux marins",
        "tags": [],
        "translations": [
            "mouette"
        ],
        "type": "simple noun"
    },
    "tas lp": {
        "description": "",
        "tags": [],
        "translations": [
            "mer",
            "ocean"
        ],
        "type": "simple noun"
    },
    "tas lam": {
        "description": "respirer de l'air frais, se sentir purge",
        "tags": [],
        "translations": [],
        "type": "simple noun"
    },
    "eli na": {
        "description": "animal semi aquatique",
        "tags": [],
        "translations": [
            "grenouille",
            "poisson"
        ],
        "type": "simple noun"
    },
    "yfan hu": {
        "description": "deformation d'un objet mou",
        "type": "simple noun",
        "tags": [],
        "translations": [
            "bosse"
        ]
    },
    "hu": {
        "description": "deformation, resultat de pression ou de contact entre deux objets",
        "tags": [],
        "translations": [
            "traces"
        ],
        "type": "class"
    },
    "nei hu": {
        "description": "contact bref qui perturbe legerement l'animal",
        "tags": [],
        "translations": [
            "traces",
            "contact"
        ],
        "type": "simple noun"
    },
    "tsis hu": {
        "description": "marques d'abrasement, marques dues a du frottement",
        "tags": [],
        "translations": [
            "rayures"
        ],
        "type": "simple noun"
    },
    "envie-servir": {
        "description": "",
        "tags": [
            "p"
        ],
        "translations": [],
        "type": "color"
    },
    "envie-servir lam": {
        "description": "",
        "tags": [
            "p"
        ],
        "translations": [
            "fonctionnant"
        ],
        "type": "simple noun"
    },
    "nei tc": {
        "description": "vehicule rapide et peu encombrant, souvent motorise",
        "tags": [],
        "translations": [
            "scooter",
            "moto",
            "trotinette",
            "skateboard"
        ],
        "type": "simple noun"
    },
    "yfan sb": {
        "description": "",
        "tags": [],
        "translations": [
            "eponge"
        ],
        "type": "simple noun"
    },
    "sb": {
        "description": "objet solide et manipulable",
        "tags": [],
        "translations": [
            "objet"
        ],
        "type": "class"
    },
    "traditionnel-nuksena": {
        "description": "",
        "tags": [
            "p"
        ],
        "translations": [],
        "type": "color"
    },
    "sei traditionnel-nuksena so": {
        "description": "histoire traditionnelle, conte",
        "tags": [
            "p"
        ],
        "translations": [
            "conte",
            "recit",
            "histoire"
        ],
        "type": "simple noun"
    },
    "bien-famille na": {
        "description": "",
        "tags": [
            "p"
        ],
        "translations": [
            "famille"
        ],
        "type": "simple noun"
    },
    "bien-pays na": {
        "description": "",
        "tags": [
            "p"
        ],
        "translations": [
            "service publique"
        ],
        "type": "simple noun"
    },
    "regret-empathique": {
        "description": "",
        "tags": [
            "p"
        ],
        "translations": [],
        "type": "color"
    },
    "djee": {
        "description": "essayer de faire quelque chose, avoir quelque chose de planifie et s'y mettre",
        "tags": [],
        "translations": [
            "planifier"
        ],
        "type": "color"
    },
    "djee min": {
        "description": "",
        "tags": [],
        "translations": [
            "jour",
            "journee"
        ],
        "type": "simple noun"
    },
    "netku": {
        "description": "chauffer au soleil, se prelasser",
        "tags": [],
        "translations": [
            "tranquille",
            "en plein air"
        ],
        "type": "color"
    },
    "netku min": {
        "description": "ensoleillement, periode de la journee",
        "tags": [],
        "translations": [
            "journee",
            "jour",
            "beau temps"
        ],
        "type": "simple noun"
    },
    "discussion-sentiment": {
        "description": "",
        "tags": [
            "p"
        ],
        "translations": [],
        "type": "color"
    },
    "discussion-sentiment lam": {
        "description": "",
        "tags": [
            "p"
        ],
        "translations": [
            "a coeur ouvert"
        ],
        "type": "simple noun"
    },
    "discussion-sentiment na": {
        "description": "",
        "tags": [
            "p"
        ],
        "translations": [
            "ami"
        ],
        "type": "simple noun"
    },
    "courbatures-maladie": {
        "description": "",
        "tags": [
            "p"
        ],
        "translations": [
            "courbatures"
        ],
        "type": "color"
    },
    "courbatures-sport": {
        "description": "",
        "tags": [
            "p"
        ],
        "translations": [
            "courbatures"
        ],
        "type": "color"
    },
    "qa": {
        "description": "",
        "tags": [],
        "translations": [
            "pensee"
        ],
        "type": "class"
    },
    "vouloir-contester": {
        "description": "",
        "tags": [
            "p"
        ],
        "translations": [],
        "type": "color"
    },
    "vouloir-contester so": {
        "description": "",
        "tags": [
            "p"
        ],
        "translations": [
            "contester"
        ],
        "type": "simple noun"
    },
    "hae": {
        "description": "le plat est apetissant, je me rejouis a l'idee de manger",
        "tags": [],
        "translations": [
            "apetissant",
            "faim"
        ],
        "type": "color"
    },
    "hae ga": {
        "description": "",
        "tags": [],
        "translations": [
            "bon",
            "apetissant",
            "bonne bouffe"
        ],
        "type": "simple noun"
    },
    "hat": {
        "description": "notion d'etre proche de son audience, d'apprecier leur compagnie. Celebre / Famous avec une connotation tres positive (opinion publique favorable)",
        "tags": [],
        "translations": [
            "celebre",
            "connu",
            "apprecie"
        ],
        "type": "color"
    },
    "hat sai": {
        "description": "",
        "tags": [],
        "translations": [
            "chanson"
        ],
        "type": "simple noun"
    },
    "hat so": {
        "description": "notion de populaire : chanson populaire",
        "tags": [],
        "translations": [
            "chanson"
        ],
        "type": "simple noun"
    },
    "hat na": {
        "description": "",
        "tags": [],
        "translations": [
            "chanteur"
        ],
        "type": "simple noun"
    },
    "hat lam": {
        "description": "plaisir de chanter en publique, d'avoir une audience et de se sentir proche d'une audience",
        "tags": [],
        "translations": [],
        "type": "simple noun"
    },
    "hae sbn": {
        "description": "",
        "tags": [],
        "translations": [
            "gout",
            "bon"
        ],
        "type": "simple noun"
    },
    "joj": {
        "description": "",
        "tags": [],
        "translations": [
            "fonction"
        ],
        "type": "class"
    },
    "lu": {
        "description": "",
        "tags": [],
        "translations": [
            "caracteristiques"
        ],
        "type": "class"
    },
    "pieds-eau": {
        "description": "",
        "tags": [
            "p"
        ],
        "translations": [
            "mettre un pied dans l'eau froide"
        ],
        "type": "color"
    },
    "pieds-eau lam": {
        "description": "",
        "tags": [
            "p"
        ],
        "translations": [
            "s'appreter a se lancer dans une activite challengeante",
            "a mettre un pied dans l'eau froide"
        ],
        "type": "simple noun"
    },
    "pieds-eau sbn": {
        "description": "",
        "tags": [
            "p"
        ],
        "translations": [
            "avoir un pied dans l'eau froide"
        ],
        "type": "simple noun"
    },
    "pieds-eau-deja": {
        "description": "",
        "tags": [
            "p"
        ],
        "translations": [
            "j'essaie de m'habituer a l'eau froide"
        ],
        "type": "color"
    },
    "pieds-eau-deja lam": {
        "description": "",
        "tags": [
            "p"
        ],
        "translations": [
            "s'habituer a une situation",
            "s'habituer"
        ],
        "type": "simple noun"
    },
    "pieds-eau-deja sbn": {
        "description": "",
        "tags": [
            "p"
        ],
        "translations": [
            "s'habituer a une sensation",
            "s'habituer"
        ],
        "type": "simple noun"
    },
    "sja na": {
        "description": "",
        "tags": [],
        "translations": [
            "ami"
        ],
        "type": "simple noun"
    },
    "regret-inefficacite": {
        "description": "",
        "type": "color",
        "tags": [
            "p"
        ],
        "translations": []
    },
    "nalc na": {
        "description": "",
        "tags": [],
        "translations": [
            "capture"
        ],
        "type": "simple noun"
    },
    "nalc lam": {
        "description": "",
        "tags": [],
        "translations": [
            "reussir a atteindre"
        ],
        "type": "simple noun"
    },
    "mla_l": {
        "description": "",
        "tags": [],
        "translations": [
            "gratitude \"il est gentil\"",
            "gratitude"
        ],
        "type": "color"
    },
    "dawi": {
        "description": "",
        "tags": [],
        "translations": [
            "laisser une impression mixte",
            "marquer"
        ],
        "type": "color"
    },
    "dawi tek": {
        "description": "",
        "type": "simple noun",
        "tags": [],
        "translations": [
            "suffixe de positivite"
        ]
    },
    "lam tek": {
        "description": "",
        "tags": [],
        "translations": [
            "mot couleur",
            "couleur"
        ],
        "type": "simple noun"
    },
    "ko tek": {
        "description": "",
        "tags": [],
        "translations": [
            "mot de classe",
            "classe"
        ],
        "type": "simple noun"
    },
    "tek": {
        "description": "",
        "tags": [],
        "translations": [
            "symbole"
        ],
        "type": "class"
    },
    "kju tek": {
        "description": "",
        "tags": [],
        "translations": [
            "marqueur de cas grammatical",
            "cas"
        ],
        "type": "simple noun"
    },
    "qa tek": {
        "description": "",
        "tags": [],
        "translations": [
            "suffixe \"temporel\""
        ],
        "type": "simple noun"
    },
    "tsa tek": {
        "description": "",
        "tags": [],
        "translations": [
            "nom"
        ],
        "type": "simple noun"
    },
    "forte-impression-amicale": {
        "description": "",
        "tags": [
            "p"
        ],
        "translations": [
            "impression amicale",
            "marquer"
        ],
        "type": "simple noun"
    },
    "eli si": {
        "description": "",
        "tags": [],
        "translations": [
            "douche"
        ],
        "type": "simple noun"
    },
    "gv": {
        "description": "",
        "tags": [],
        "translations": [
            "procedure",
            "plan",
            "methode",
            "technique"
        ],
        "type": "class"
    },
    "kp": {
        "description": "partie superieure d'un objet ou d'une structure",
        "tags": [],
        "translations": [
            "haut",
            "position relative"
        ],
        "type": "color"
    },
    "tbn": {
        "description": "comme kp, partie inferieure d'un objet ou d'une structure",
        "tags": [],
        "translations": [
            "bas",
            "position relative"
        ],
        "type": "color"
    },
    "nci": {
        "description": "",
        "tags": [
            "couleur"
        ],
        "translations": [
            "cyan"
        ],
        "type": "color"
    },
    "nci lp": {
        "description": "",
        "tags": [],
        "translations": [
            "ciel"
        ],
        "type": "simple noun"
    },
    "fin": {
        "description": "",
        "tags": [],
        "translations": [
            "tissage",
            "ensemble d'objets fins et longs (texture)"
        ],
        "type": "class"
    },
    "daat": {
        "description": "etre enfin a l'ombre d'un arbre aux larges feuilles alors que le soleil tape fort",
        "tags": [],
        "translations": [
            "content de sa situation",
            "enfin a l'ombre",
            "leger soulagement"
        ],
        "type": "color"
    },
    "daat fin": {
        "description": "branches d'un arbre specifique",
        "tags": [],
        "translations": [
            "branches"
        ],
        "type": "simple noun"
    },
    "kp fin": {
        "description": "",
        "tags": [],
        "translations": [
            "cheveux"
        ],
        "type": "simple noun"
    },
    "ki f jus": {
        "description": "",
        "tags": [],
        "translations": [
            "yeux",
            "oeil"
        ],
        "type": "simple noun"
    },
    "daat teo": {
        "description": "",
        "tags": [],
        "translations": [
            "arbre"
        ],
        "type": "simple noun"
    },
    "teo": {
        "description": "",
        "tags": [],
        "translations": [
            "lieu couvert",
            "interieur",
            "batiment",
            "lieu"
        ],
        "type": "class"
    },
    "tao": {
        "description": "",
        "tags": [],
        "translations": [
            "territoire",
            "pays",
            "region",
            "lieu"
        ],
        "type": "class"
    },
    "hae teo": {
        "description": "",
        "tags": [],
        "translations": [
            "restaurant"
        ],
        "type": "simple noun"
    },
    "nci teo": {
        "description": "partie horizontalement superieure, la plus proche du ciel",
        "tags": [],
        "translations": [
            "haut",
            "dessus",
            "etage",
            "salle cyan"
        ],
        "type": "simple noun"
    },
    "netku lp": {
        "description": "",
        "tags": [],
        "translations": [
            "terrasse",
            "plage"
        ],
        "type": "simple noun"
    },
    "thi": {
        "description": "",
        "tags": [],
        "translations": [
            "chaud",
            "tiede"
        ],
        "type": "color"
    },
    "thi sbn": {
        "description": "",
        "tags": [],
        "translations": [
            "chaleur"
        ],
        "type": "simple noun"
    },
    "gy": {
        "description": "",
        "tags": [],
        "translations": [
            "froid",
            "frais"
        ],
        "type": "color"
    },
    "concentration-realisation": {
        "description": "",
        "tags": [
            "p"
        ],
        "translations": [],
        "type": "color"
    },
    "concentration-realisation na": {
        "description": "",
        "tags": [
            "p"
        ],
        "translations": [
            "travailleur"
        ],
        "type": "simple noun"
    },
    "concentration-realisation teo": {
        "description": "",
        "tags": [
            "p"
        ],
        "translations": [
            "lieu de travail"
        ],
        "type": "simple noun"
    },
    "fatigue-envie-pas-envie": {
        "description": "fatigue on veut pas mais on le fait quand meme",
        "tags": [
            "p"
        ],
        "translations": [],
        "type": "color"
    },
    "fatigue-envie-pas-envie na": {
        "description": "",
        "tags": [
            "p"
        ],
        "translations": [
            "travailleur"
        ],
        "type": "simple noun"
    },
    "fatigue-envie-pas-envie lam": {
        "description": "",
        "tags": [
            "p"
        ],
        "translations": [
            "envie d'aller travailleur",
            "flemme"
        ],
        "type": "simple noun"
    },
    "gen": {
        "description": "satisfait du resultat d'un processus d'equilibrage qui implique des parametres instables a stabiliser.",
        "tags": [],
        "translations": [
            "reussit",
            "satisfait",
            "equilibre"
        ],
        "type": "color"
    },
    "constance": {
        "description": "",
        "tags": [
            "p"
        ],
        "translations": [
            "constance",
            "constant"
        ],
        "type": "color"
    },
    "irregularite": {
        "description": "",
        "tags": [
            "p"
        ],
        "translations": [
            "unsettling",
            "irregulier",
            "irregularite"
        ],
        "type": "color"
    },
    "djee so": {
        "description": "chose qu'on a envie de faire / qu'on prevoit pour la journee",
        "type": "simple noun",
        "tags": [],
        "translations": [
            "plan",
            "instructions",
            "projet"
        ]
    },
    "djee lam": {
        "description": "envie de faire un tache planifiee sur une journee ou moins",
        "type": "simple noun",
        "tags": [],
        "translations": [
            "motivation"
        ]
    },
    "dee": {
        "description": "",
        "tags": [],
        "translations": [
            "etre perdu dans ses pensees"
        ],
        "type": "color"
    },
    "dee si": {
        "description": "",
        "tags": [],
        "translations": [
            "programme informatique"
        ],
        "type": "simple noun"
    },
    "fcwb": {
        "description": "perdre une chose importante et chercher a tout prix un moyen de le recuperer / ramener a l'etat d'origine",
        "tags": [],
        "translations": [
            "stress"
        ],
        "type": "color"
    },
    "njyewe": {
        "description": "assis sur un lit, au bord d'une falaise, avec vue sur la ville",
        "tags": [],
        "translations": [
            "contempler"
        ],
        "type": "color"
    },
    "njyewe ksen": {
        "description": "",
        "type": "simple noun",
        "tags": [],
        "translations": [
            "skyline"
        ]
    },
    "njyewe lp": {
        "description": "",
        "tags": [],
        "translations": [
            "aire urbaine"
        ],
        "type": "simple noun"
    },
    "cine na": {
        "description": "",
        "type": "simple noun",
        "tags": [],
        "translations": [
            "peuple"
        ]
    },
    "cine": {
        "description": "sentiment de fierte envers une nation, un groupe de personnes organise d'envergure majeure et reconnue",
        "type": "color",
        "tags": [],
        "translations": [
            "fierte"
        ]
    },
    "cine so": {
        "description": "histoire des nuksena",
        "type": "simple noun",
        "tags": [],
        "translations": [
            "histoire"
        ]
    },
    "sheup": {
        "description": "peur qu'un conflit eclate avec des parties externes (non nationales) (= conflit), et des consequences sur l'integrite de la societe",
        "type": "color",
        "tags": [],
        "translations": [
            "peur du conflit",
            "conflit"
        ]
    },
    "sheup na": {
        "description": "",
        "type": "simple noun",
        "tags": [],
        "translations": [
            "espion"
        ]
    },
    "ksen": {
        "description": "structure d'elements constitutifs organises de maniere a ce qu'une logique soit perceptible en l'observant de loin, dans son ensemble, sans necessairement remarquer les petits details (tas de pierre, oeuvre d'art a grande echelle, amenagements de jardin)",
        "tags": [],
        "translations": [],
        "type": "class"
    },
    "dli": {
        "description": "objet qui a une structure tres complexe",
        "tags": [],
        "translations": [
            "bijoux",
            "gravure",
            "ouvrage",
            "oeuvre d'art"
        ],
        "type": "class"
    },
    "nyo": {
        "description": "collection d'informations structurees",
        "tags": [],
        "translations": [],
        "type": "class"
    },
    "sem": {
        "description": "",
        "tags": [],
        "translations": [
            "intention"
        ],
        "type": "class"
    },
    "lu_": {
        "description": "element qui n'est pas deplacable, dans lequel on peut inserer des trucs",
        "tags": [],
        "translations": [
            "trou"
        ],
        "type": "class"
    },
    "tas lu_": {
        "description": "",
        "tags": [],
        "translations": [
            "vortex"
        ],
        "type": "simple noun"
    },
    "tas tc lu_": {
        "description": "",
        "tags": [],
        "translations": [
            "trou dans la coque"
        ],
        "type": "simple noun"
    },
    "hae na": {
        "description": "",
        "tags": [],
        "translations": [
            "cusinier",
            "client"
        ],
        "type": "simple noun"
    },
    "hae s na": {
        "description": "",
        "tags": [],
        "translations": [
            "cuisinier"
        ],
        "type": "simple noun"
    },
    "hewa": {
        "description": "une information qu'on vient de me donner me perturbe dans le sens ou elle est incoherente, ou ne fait pas sens dans ma vision du monde",
        "type": "color",
        "tags": [],
        "translations": [
            "incoherent"
        ]
    },
    "hewa so": {
        "description": "argumentation / contestation d'un statement",
        "type": "simple noun",
        "tags": [],
        "translations": [
            "contestation"
        ]
    },
    "hewa lam": {
        "description": "penser que ce qui a ete affirme est factuellement faux",
        "tags": [],
        "translations": [
            "ne pas etre d'accord"
        ],
        "type": "simple noun"
    },
    "qav": {
        "description": "perdre quelque chose, etre desespere, et ne rien faire",
        "tags": [],
        "translations": [
            "stress",
            "desespoir"
        ],
        "type": "color"
    },
    "jubn": {
        "description": "se sentir chez soi",
        "tags": [],
        "translations": [],
        "type": "color"
    },
    "jubn teo": {
        "description": "",
        "tags": [],
        "translations": [
            "logement",
            "maison",
            "appartement",
            "chez soi"
        ],
        "type": "simple noun"
    },
    "jubn tao": {
        "description": "",
        "tags": [],
        "translations": [
            "ville de residence",
            "patrie"
        ],
        "type": "simple noun"
    },
    "juebn teo": {
        "description": "",
        "type": "simple noun",
        "tags": [],
        "translations": [
            "maison",
            "appartement",
            "maison de son enfance"
        ]
    },
    "juebn tao": {
        "description": "",
        "tags": [],
        "translations": [
            "ville natale",
            "pays d'origine"
        ],
        "type": "simple noun"
    },
    "juebn": {
        "description": "se sentir chez soi, couple a de la nostalgie : ce qui nous faisais nous sentir chez nous par le passe (maison d'enfance, village...)",
        "type": "color",
        "tags": [],
        "translations": [
            "nostalgie"
        ]
    },
    "nise": {
        "description": "satisfaction du travail d'equipe",
        "tags": [],
        "translations": [
            "travail d'equipe",
            "groupe"
        ],
        "type": "color"
    },
    "nise lam": {
        "description": "se sentir dans un groupe de travail qui avance efficacement, se sentir coordonne avec les autres",
        "tags": [],
        "translations": [
            "travail d'equipe",
            "cooperation",
            "groupe"
        ],
        "type": "simple noun"
    },
    "nise na": {
        "description": "",
        "tags": [],
        "translations": [
            "equipier",
            "vendeur",
            "equipe",
            "groupe"
        ],
        "type": "simple noun"
    },
    "nise ko": {
        "description": "l'equipe consideree comme partie d'un systeme d'equipes (entreprise, usine, sport...)",
        "tags": [],
        "translations": [
            "equipe",
            "groupe"
        ],
        "type": "simple noun"
    },
    "get": {
        "description": "spoiled / not yet edible food",
        "type": "class",
        "tags": [],
        "translations": [
            "spoiled food"
        ]
    },
    "leeso get": {
        "description": "",
        "type": "simple noun",
        "tags": [],
        "translations": []
    },
    "ohaw": {
        "description": "s'attendre a voir quelque chose, mais ne pas le voir. Vouloir que la chose soit la pour poursuivre l'activite",
        "tags": [],
        "translations": [
            "vide",
            "absent"
        ],
        "type": "color"
    },
    "spy": {
        "description": "quelqu'un nous annonce qu'il y a quelque chose, on ne le voit pas, ou on ne le comprend pas",
        "tags": [],
        "translations": [
            "vide",
            "absent",
            "incompris"
        ],
        "type": "color"
    },
    "deh": {
        "description": "rugeux et qui s'effrite en poudre au contact",
        "tags": [],
        "translations": [],
        "type": "color"
    },
    "deh lp": {
        "description": "",
        "tags": [],
        "translations": [
            "roche",
            "bitume"
        ],
        "type": "simple noun"
    },
    "deh sb": {
        "description": "",
        "tags": [],
        "translations": [
            "pierre"
        ],
        "type": "simple noun"
    },
    "deh sak": {
        "description": "poussiere d'origine rocheuse, exterieure",
        "tags": [],
        "translations": [
            "poussiere"
        ],
        "type": "simple noun"
    },
    "aisi": {
        "description": "etre dans le flow de la musique, ecouter et apprecier, analyser ou suivre le rythme",
        "tags": [],
        "translations": [],
        "type": "color"
    },
    "aisi so": {
        "description": "insiste sur l'aspect \"semantique\" du morceau, il est porteur de sens",
        "tags": [],
        "translations": [
            "chanson",
            "musique"
        ],
        "type": "simple noun"
    },
    "aisi sai": {
        "description": "",
        "tags": [],
        "translations": [
            "musique",
            "chanson"
        ],
        "type": "simple noun"
    },
    "eli sije_": {
        "description": "",
        "type": "simple noun",
        "tags": [],
        "translations": [
            "eau croupie"
        ]
    },
    "sije_": {
        "description": "toute boisson jugee inbuvable, non potable, toxique, perimee",
        "type": "class",
        "tags": [],
        "translations": [
            "perime",
            "non-potable"
        ]
    },
    "kwah": {
        "description": "agite par le rythme de la musique, suivre le rythme et etre engage dedans",
        "tags": [],
        "translations": [],
        "type": "color"
    },
    "kwah sai": {
        "description": "",
        "tags": [],
        "translations": [
            "musique",
            "chanson",
            "concert"
        ],
        "type": "simple noun"
    },
    "kwah teo": {
        "description": "",
        "tags": [],
        "translations": [
            "salle de concert active",
            "boite de nuit",
            "soiree"
        ],
        "type": "simple noun"
    },
    "kwah qubn": {
        "description": "soirees parking, fetes en exterieur",
        "tags": [],
        "translations": [
            "soiree",
            "soiree a ciel ouvert"
        ],
        "type": "simple noun"
    },
    "qubn": {
        "description": "lieu ou se deroule un evenement, delimite par la portee de l'evenement (peut etre en exterieur, les gens peuvent se deplacer dans un certain rayon pour poursuivre l'activite)",
        "tags": [],
        "translations": [
            "lieu"
        ],
        "type": "class"
    },
    "hat qubn": {
        "description": "concert a ciel ouvert, salle de concert semi couverte",
        "tags": [],
        "translations": [
            "concert",
            "spectacle"
        ],
        "type": "simple noun"
    },
    "qwbn na": {
        "description": "",
        "tags": [],
        "translations": [
            "poisson"
        ],
        "type": "simple noun"
    },
    "tjo": {
        "description": "portion de quelque chose qui a ete segmente mais conserve l'essentiel de ses proprietes",
        "tags": [],
        "translations": [
            "part",
            "morceau",
            "fragment"
        ],
        "type": "class"
    },
    "yfan ga tjo": {
        "description": "",
        "tags": [],
        "translations": [
            "part de gateau"
        ],
        "type": "simple noun"
    },
    "yfan tjo": {
        "description": "",
        "tags": [],
        "translations": [
            "part de gateau"
        ],
        "type": "simple noun"
    },
    "gen lam": {
        "description": "satisfait du resultat d'un processus d'equilibrage qui implique des parametres instables a stabiliser.",
        "tags": [],
        "translations": [
            "satisfait du parametrage",
            "reussir",
            "satisfait"
        ],
        "type": "simple noun"
    },
    "sugen": {
        "description": "sentiment de gratitude apres \"acquittement\" (de la part de celui qui s'acquitte de quelque chose)",
        "tags": [],
        "translations": [],
        "type": "color"
    },
    "sugen lam": {
        "description": "sentiment de gratitude apres \"acquittement\" (de la part de celui qui s'acquitte de quelque chose)",
        "tags": [],
        "translations": [
            "even",
            "feeling even",
            "etre quitte",
            "gratitude"
        ],
        "type": "simple noun"
    },
    "qwbn lam": {
        "description": "se sentir flotter, nager lentement ou rester inerte, regarder un paysage comme le ciel ou le fond de l'eau",
        "tags": [],
        "translations": [
            "tranquille"
        ],
        "type": "simple noun"
    },
    "na kju": {
        "description": "",
        "tags": [],
        "translations": [
            "comportement"
        ],
        "type": "simple noun"
    },
    "eli kju": {
        "description": "techniques en rapport avec l'eau : nage mais aussi eclaboussures, plongee",
        "tags": [],
        "translations": [
            "nage",
            "plongee"
        ],
        "type": "simple noun"
    },
    "tei": {
        "description": "element qui se demarque et qui peut servir de support",
        "tags": [],
        "translations": [],
        "type": "class"
    },
    "hae tei": {
        "description": "",
        "tags": [],
        "translations": [
            "table",
            "chaise"
        ],
        "type": "simple noun"
    },
    "nukse tei": {
        "description": "",
        "tags": [],
        "translations": [
            "chaise",
            "chaise longue",
            "transat"
        ],
        "type": "simple noun"
    },
    "qispe jus": {
        "description": "",
        "tags": [],
        "translations": [
            "crayon",
            "stylo"
        ],
        "type": "simple noun"
    },
    "eli dek": {
        "description": "",
        "tags": [],
        "translations": [
            "flaque d'eau",
            "flaque"
        ],
        "type": "simple noun"
    },
    "fsah lp": {
        "description": "",
        "type": "simple noun",
        "tags": [],
        "translations": [
            "prairie"
        ]
    },
    "fsah": {
        "description": "petit et attache a une surface",
        "type": "color",
        "tags": [],
        "translations": []
    },
    "fsah sbn": {
        "description": "",
        "tags": [],
        "translations": [
            "doux"
        ],
        "type": "simple noun"
    },
    "fsah fin": {
        "description": "",
        "tags": [],
        "translations": [
            "poils",
            "laine",
            "tissu"
        ],
        "type": "simple noun"
    },
    "nea": {
        "description": "",
        "tags": [],
        "translations": [
            "sommeil"
        ],
        "type": "color"
    },
    "nea min": {
        "description": "",
        "tags": [],
        "translations": [
            "dormir",
            "nuit"
        ],
        "type": "simple noun"
    },
    "helo": {
        "description": "periode de temps\r\n",
        "type": "class",
        "tags": [],
        "translations": []
    },
    "nea sbn": {
        "description": "",
        "tags": [],
        "translations": [
            "fatigue"
        ],
        "type": "simple noun"
    },
    "nea fin": {
        "description": "",
        "tags": [],
        "translations": [
            "laine"
        ],
        "type": "simple noun"
    },
    "nea til": {
        "description": "",
        "tags": [],
        "translations": [
            "alpaga"
        ],
        "type": "simple noun"
    },
    "nea hu": {
        "description": "contact avec de la laine ou une surface douce",
        "tags": [],
        "translations": [],
        "type": "simple noun"
    },
    "nea hu sbn": {
        "description": "",
        "tags": [],
        "translations": [
            "doux"
        ],
        "type": "simple noun"
    },
    "njb": {
        "description": "phenomene de grande ampleur, modification environnementale qui affecte (physiquement) les personnes",
        "type": "class",
        "tags": [],
        "translations": [
            "partout autours"
        ]
    },
    "eli njb": {
        "description": "",
        "tags": [],
        "translations": [
            "pluie",
            "eclaboussure"
        ],
        "type": "simple noun"
    },
    "eli jus": {
        "description": "n'importe quel source d'eau deplacable",
        "tags": [],
        "translations": [
            "jet d'eau",
            "tuyau d'arrosage"
        ],
        "type": "simple noun"
    },
    "eli ko": {
        "description": "",
        "tags": [],
        "translations": [
            "bouteille d'eau",
            "sceau",
            "verre"
        ],
        "type": "simple noun"
    },
    "eli ko jus": {
        "description": "",
        "tags": [],
        "translations": [
            "sceau"
        ],
        "type": "simple noun"
    },
    "nas scy": {
        "description": "",
        "tags": [],
        "translations": [
            "oranges"
        ],
        "type": "simple noun"
    },
    "scy": {
        "description": "nourriture acide, tres juteuse ou froide : fruits, legumes, glaces",
        "type": "simple noun",
        "tags": [],
        "translations": [
            "nourriture"
        ]
    },
    "tscu": {
        "description": "satisfait du resultat alors qu'on s'attendait a pire",
        "tags": [],
        "translations": [],
        "type": "color"
    },
    "tscu min": {
        "description": "",
        "tags": [],
        "translations": [
            "reussir",
            "reussite",
            "plutot reussir"
        ],
        "type": "simple noun"
    },
    "thi njb": {
        "description": "",
        "tags": [],
        "translations": [
            "soleil",
            "jour",
            "journee"
        ],
        "type": "simple noun"
    },
    "thi min": {
        "description": "",
        "tags": [],
        "translations": [
            "jour",
            "journee"
        ],
        "type": "simple noun"
    },
    "nea sai": {
        "description": "",
        "tags": [],
        "translations": [
            "ronflements",
            "ronfler"
        ],
        "type": "simple noun"
    },
    "nea til sai": {
        "description": "cri de l'alpaga",
        "tags": [],
        "translations": [],
        "type": "simple noun"
    },
    "scuo": {
        "description": "individuel,seul",
        "tags": [],
        "translations": [
            "seul",
            "solitaire"
        ],
        "type": "color"
    },
    "scuo tc": {
        "description": "",
        "tags": [],
        "translations": [
            "vehicule individuel",
            "voiture",
            "moto"
        ],
        "type": "simple noun"
    },
    "nei gv": {
        "description": "",
        "tags": [],
        "translations": [
            "evitement",
            "strategie d'evitement"
        ],
        "type": "simple noun"
    },
    "ejwe_": {
        "description": "chanter, s'exprimer, dans le flow. Etre a fond dedans",
        "type": "color",
        "tags": [],
        "translations": []
    },
    "ejwe_ na": {
        "description": "",
        "type": "simple noun",
        "tags": [],
        "translations": [
            "chanteur"
        ]
    },
    "ejwe_ lam": {
        "description": "etre a fond dans ce qu'on fait, etre immerge",
        "type": "simple noun",
        "tags": [],
        "translations": [
            "concentration",
            "immertion"
        ]
    },
    "gebq na": {
        "description": "",
        "type": "simple noun",
        "tags": [],
        "translations": [
            "entreprise",
            "societe",
            "compagnie"
        ]
    },
    "gebq teo": {
        "description": "",
        "type": "simple noun",
        "tags": [
            "p"
        ],
        "translations": [
            "usine",
            "lieu de travail"
        ]
    },
    "gebq": {
        "description": "penser au gain potentiel",
        "type": "color",
        "tags": [],
        "translations": [
            "benefique",
            "economiquement benefique"
        ]
    },
    "gebq fjp": {
        "description": "",
        "tags": [],
        "translations": [
            "benefice",
            "gain"
        ],
        "type": "simple noun"
    },
    "fjp tek": {
        "description": "",
        "tags": [],
        "translations": [
            "chiffre",
            "nombre"
        ],
        "type": "simple noun"
    },
    "gebq lam": {
        "description": "appat du gain, motive a participer a un plan qui mene a un gain",
        "tags": [],
        "translations": [
            "enthousiaste",
            "motive"
        ],
        "type": "simple noun"
    },
    "ukto": {
        "description": "interagir avec un systeme organise par des personnes d'une societe (systeme auquel on est habitue, pas decouverte (il y a un autre mot pour ca))",
        "tags": [],
        "translations": [
            "integrer"
        ],
        "type": "color"
    },
    "ukto jus": {
        "description": "",
        "tags": [],
        "translations": [
            "portable",
            "smartphone",
            "telephone portable"
        ],
        "type": "simple noun"
    },
    "tas sbn": {
        "description": "",
        "tags": [],
        "translations": [
            "vent marin",
            "vent"
        ],
        "type": "simple noun"
    },
    "tas sai": {
        "description": "bruit de la mer, des vagues, des mouettes",
        "tags": [],
        "translations": [
            "vagues",
            "cri des mouettes",
            "vent marin"
        ],
        "type": "simple noun"
    },
    "hae sem": {
        "description": "",
        "tags": [],
        "translations": [
            "cuisiner",
            "faire a manger",
            "aller chasser"
        ],
        "type": "simple noun"
    },
    "nea sem": {
        "description": "",
        "tags": [],
        "translations": [
            "fatigue",
            "aller dormir"
        ],
        "type": "simple noun"
    },
    "lam ki": {
        "description": "couleur, sensation \"visuelle\" :: caracteristique d'un objet",
        "tags": [
            "couleur"
        ],
        "translations": [
            "couleur"
        ],
        "type": "simple noun"
    },
    "gp": {
        "description": "placeholder, element quasiment tout a fait indetermine, quoi que en general un objet",
        "tags": [],
        "translations": [],
        "type": "class"
    },
    "jea": {
        "description": "soulagement / relief, une tache difficile qui a l'air insurmontable mais avec de l'aide elle n'a plus l'air si difficile",
        "tags": [],
        "translations": [
            "soulagement"
        ],
        "type": "color"
    },
    "jea lam": {
        "description": "une tache difficile qui a l'air insurmontable mais avec de l'aide elle n'a plus l'air si difficile",
        "tags": [],
        "translations": [
            "soulagement"
        ],
        "type": "simple noun"
    },
    "jea min": {
        "description": "porter assistance, aider quelqu'un a une tache",
        "tags": [],
        "translations": [
            "aider",
            "assistance"
        ],
        "type": "simple noun"
    },
    "jea sai": {
        "description": "",
        "tags": [],
        "translations": [
            "demander de l'aide"
        ],
        "type": "simple noun"
    },
    "jea f so": {
        "description": "",
        "tags": [],
        "translations": [
            "demander de l'aide"
        ],
        "type": "simple noun"
    },
    "jea so": {
        "description": "expression du soulagement",
        "tags": [],
        "translations": [],
        "type": "simple noun"
    },
    "-vl": {
        "description": "incertain, joue le role des guillemets dans le contexte : j'ai un \"cheval\". = j'ai une espece de cheval.",
        "tags": [
            "suffixe"
        ],
        "translations": [
            "incertain"
        ],
        "type": "special"
    },
    "juck": {
        "description": "stress a l'idee de paraitre en publique pour chanter",
        "tags": [],
        "translations": [
            "stress"
        ],
        "type": "color"
    },
    "juck na": {
        "description": "connotation de chanteur debutant ou chanteur connu qui avoue publiquement avoir le trac",
        "tags": [],
        "translations": [
            "chanteur"
        ],
        "type": "simple noun"
    },
    "juck lam": {
        "description": "avoir le trac",
        "tags": [],
        "translations": [
            "trac"
        ],
        "type": "simple noun"
    },
    "qispe sb": {
        "description": "support d'ecriture, le type de support est indique via des proprietes supplementaires",
        "type": "simple noun",
        "tags": [],
        "translations": [
            "feuille de papier",
            "support",
            "tablette",
            "ardoise",
            "feuille"
        ]
    },
    "dek": {
        "description": "artefact sur une regularite",
        "type": "class",
        "tags": [],
        "translations": [
            "irregulier"
        ]
    },
    "fuh": {
        "description": "angoisse liee a l'obscurite, legere paranoia a l'idee de se faire attaquer",
        "tags": [],
        "translations": [
            "sombre"
        ],
        "type": "color"
    },
    "fuh lam": {
        "description": "angoisse liee a l'obscurite, legere paranoia a l'idee de se faire attaquer",
        "tags": [],
        "translations": [
            "angoisse",
            "peur",
            "paranoia"
        ],
        "type": "simple noun"
    },
    "fuh ki": {
        "description": "",
        "tags": [],
        "translations": [
            "obscurite",
            "sombre",
            "noir"
        ],
        "type": "simple noun"
    },
    "ki si": {
        "description": "",
        "tags": [],
        "translations": [
            "ecran"
        ],
        "type": "class"
    },
    "des": {
        "description": "peur de se faire surprendre en cherchant quelqu'un au cache cache / s'attendre a voir quelqu'un a un moment donne",
        "tags": [],
        "translations": [
            "alerte",
            "alerte (amusement)",
            "explorateur",
            "curieux"
        ],
        "type": "color"
    },
    "des min": {
        "description": "",
        "tags": [],
        "translations": [
            "recherche"
        ],
        "type": "simple noun"
    },
    "des lam": {
        "description": "peur de se faire surprendre en cherchant quelqu'un au cache cache / s'attendre a voir quelqu'un",
        "tags": [],
        "translations": [],
        "type": "simple noun"
    },
    "dahe": {
        "description": "perdu quelque chose, recherche paniquee pour le retrouver, vouloir le retrouver a tout prix",
        "tags": [],
        "translations": [
            "panique",
            "alerte",
            "recherche"
        ],
        "type": "color"
    },
    "dahe min": {
        "description": "",
        "tags": [],
        "translations": [
            "recherche",
            "panique"
        ],
        "type": "simple noun"
    },
    "dahe lam": {
        "description": "perdu quelque chose, recherche paniquee pour le retrouver, vouloir le retrouver a tout prix",
        "tags": [],
        "translations": [
            "panique",
            "stress"
        ],
        "type": "simple noun"
    },
    "twact": {
        "description": "se balader dans un coin \"parce que pourquoi pas\", etre enthousiasme a l'idee de trouver quelque chose de nouveau. Valable a l'abstrait pour la recherche d'information sans s'attendre a trouver un truc",
        "tags": [],
        "translations": [
            "recherche",
            "curieux",
            "explorant"
        ],
        "type": "color"
    },
    "daei": {
        "description": "des, mais avec une crainte plutot axee sur le fait de ne rien trouver (que sur la peur d'etre surpris)",
        "type": "color",
        "tags": [],
        "translations": [
            "cherchant"
        ]
    },
    "daei min": {
        "description": "",
        "tags": [],
        "translations": [
            "recherche"
        ],
        "type": "simple noun"
    },
    "twact min": {
        "description": "",
        "tags": [],
        "translations": [
            "recherche"
        ],
        "type": "simple noun"
    }
}